[
  {
    "id": "george",
    "agent": "George",
    "agentEmoji": "\ud83e\uddbe",
    "action": "In 12PM standup",
    "time": "12:00 PM",
    "color": "#6366f1"
  },
  {
    "id": "dwight",
    "agent": "Dwight",
    "agentEmoji": "\ud83d\udd0d",
    "action": "In 12PM standup",
    "time": "12:00 PM",
    "color": "#a855f7"
  },
  {
    "id": "kelly",
    "agent": "Kelly",
    "agentEmoji": "\ud83d\udc26",
    "action": "In 12PM standup",
    "time": "12:00 PM",
    "color": "#ec4899"
  },
  {
    "id": "rachel",
    "agent": "Rachel",
    "agentEmoji": "\ud83d\udcbc",
    "action": "In 12PM standup",
    "time": "12:00 PM",
    "color": "#3b82f6"
  },
  {
    "id": "john",
    "agent": "John",
    "agentEmoji": "\ud83d\udcc8",
    "action": "In 12PM standup",
    "time": "12:00 PM",
    "color": "#10b981"
  },
  {
    "id": "ross",
    "agent": "Ross",
    "agentEmoji": "\u2699\ufe0f",
    "action": "Adding remove-from-queue to Content tab \u2014 P0",
    "time": "11:40 AM",
    "color": "#f59e0b"
  },
  {
    "id": "pam",
    "agent": "Pam",
    "agentEmoji": "\ud83d\udccb",
    "action": "Idle \u2014 next: CRM ingestion 10PM",
    "time": "7:49 AM",
    "color": "#f472b6"
  }
]