[
  {
    "id": "george",
    "agent": "George",
    "agentEmoji": "\ud83e\uddbe",
    "action": "In 11PM standup",
    "time": "11:00 PM",
    "color": "#6366f1"
  },
  {
    "id": "dwight",
    "agent": "Dwight",
    "agentEmoji": "\ud83d\udd0d",
    "action": "Deep research: SOL Strategies Q1 + Phase positioning",
    "time": "11:00 PM",
    "color": "#a855f7"
  },
  {
    "id": "kelly",
    "agent": "Kelly",
    "agentEmoji": "\ud83d\udc26",
    "action": "In 11PM standup",
    "time": "11:00 PM",
    "color": "#ec4899"
  },
  {
    "id": "rachel",
    "agent": "Rachel",
    "agentEmoji": "\ud83d\udcbc",
    "action": "In 11PM standup",
    "time": "11:00 PM",
    "color": "#3b82f6"
  },
  {
    "id": "john",
    "agent": "John",
    "agentEmoji": "\ud83d\udcc8",
    "action": "Bear market DCA strategy optimization",
    "time": "11:00 PM",
    "color": "#10b981"
  },
  {
    "id": "ross",
    "agent": "Ross",
    "agentEmoji": "\u2699\ufe0f",
    "action": "Evaluating GitHub Agentic Workflows",
    "time": "11:00 PM",
    "color": "#f59e0b"
  },
  {
    "id": "pam",
    "agent": "Pam",
    "agentEmoji": "\ud83d\udccb",
    "action": "In 11PM standup",
    "time": "11:00 PM",
    "color": "#f472b6"
  }
]